README.rst
setup.cfg
setup.py
cdoc/__init__.py
cdoc/__main__.py
cdoc/commands.py
cdoc/logging.py
cdoc/parsing.py
cdoc/registration.py
cdoc/store_helpers.py
cross_doc.egg-info/PKG-INFO
cross_doc.egg-info/SOURCES.txt
cross_doc.egg-info/dependency_links.txt
cross_doc.egg-info/entry_points.txt
cross_doc.egg-info/top_level.txt