Metadata-Version: 1.1
Name: cross-doc
Version: 0.2.0
Summary: A comment management system for the modern world
Home-page: https://github.com/petetetete/CrossDoc
Author: Octo-Docs
Author-email: ph289@nau.edu
License: MIT
Download-URL: https://github.com/petetetete/CrossDoc/archive/0.2.0.tar.gz
Keywords: CrossDoc documentation comments storage
Platform: UNKNOWN
